{
  "workbench.colorTheme": "Light 2026",
  "workbench.preferredLightColorTheme": "Light 2026",
  "window.autoDetectColorScheme": false,
  "workbench.iconTheme": "vs-seti",
  "workbench.productIconTheme": "Default",
  "workbench.colorCustomizations": {
    "editor.background": "#FBFCF3",
    "editorGutter.background": "#EEF6DF",
    "editor.foreground": "#263027",
    "editorLineNumber.foreground": "#7D8B62",
    "editorLineNumber.activeForeground": "#5E8A2A",
    "editorCursor.foreground": "#6FAF2E",
    "editor.selectionBackground": "#D8EFB0",
    "editor.selectionForeground": "#202716",
    "editor.inactiveSelectionBackground": "#E7F5CE",
    "editor.selectionHighlightBackground": "#EEF8D9",
    "editor.lineHighlightBackground": "#F1F8E8",
    "editorGroupHeader.tabsBackground": "#EAF4D8",
    "editorGroupHeader.tabsBorder": "#9FC76A",
    "tab.activeBackground": "#FBFCF3",
    "tab.activeForeground": "#202716",
    "tab.inactiveBackground": "#E5F0D4",
    "tab.inactiveForeground": "#60724D",
    "tab.border": "#A7C977",
    "tab.activeBorder": "#79AD36",
    "tab.hoverBackground": "#F0F8E3",
    "sideBar.background": "#EAF4D8",
    "sideBar.foreground": "#263027",
    "sideBarTitle.foreground": "#202716",
    "sideBarSectionHeader.background": "#DDEDBF",
    "sideBarSectionHeader.foreground": "#587D2B",
    "sideBar.border": "#A7C977",
    "activityBar.background": "#DDEDBF",
    "activityBar.foreground": "#587D2B",
    "activityBar.inactiveForeground": "#748464",
    "activityBarBadge.background": "#B9DC74",
    "activityBarBadge.foreground": "#202716",
    "activityBar.border": "#A7C977",
    "statusBar.background": "#E4F1CF",
    "statusBar.foreground": "#202716",
    "statusBar.noFolderBackground": "#DCEBBE",
    "statusBar.debuggingBackground": "#D2E79A",
    "statusBar.debuggingForeground": "#202716",
    "statusBar.border": "#A7C977",
    "titleBar.activeBackground": "#E8F3D5",
    "titleBar.activeForeground": "#202716",
    "titleBar.inactiveBackground": "#F2F8E7",
    "titleBar.inactiveForeground": "#60724D",
    "titleBar.border": "#A7C977",
    "panel.background": "#F3F8EA",
    "panel.foreground": "#263027",
    "panelTitle.activeForeground": "#587D2B",
    "panelTitle.inactiveForeground": "#748464",
    "panel.border": "#A7C977",
    "input.background": "#FEFFF7",
    "input.foreground": "#263027",
    "input.border": "#A7C977",
    "dropdown.background": "#FEFFF7",
    "dropdown.foreground": "#263027",
    "dropdown.border": "#A7C977",
    "list.hoverBackground": "#EDF7DC",
    "list.activeSelectionBackground": "#CFEA9A",
    "list.activeSelectionForeground": "#202716",
    "list.inactiveSelectionBackground": "#E1F1C3",
    "list.inactiveSelectionForeground": "#263027",
    "focusBorder": "#79AD36",
    "contrastBorder": "#A7C977",
    "sash.hoverBorder": "#79AD36"
  }
}
